{
  "body": {
    "patternName": "inner_chest",
    "paletteName": "human025"
  },
  "makeup": {
    "patternName": "eye_shadow_square",
    "paletteName": "natural_cyan"
  },
  "left_eye": {
    "patternName": "square",
    "paletteName": "black"
  },
  "right_eye": {
    "patternName": "square",
    "paletteName": "black"
  },
  "bottomwear": {
    "patternName": "pants_solid3",
    "paletteName": "theme__032__desert_dream"
  },
  "footwear": {
    "patternName": "shoes4",
    "paletteName": "theme__032__desert_dream"
  },
  "topwear": {
    "patternName": "tshirt_gradient1",
    "paletteName": "theme__032__desert_dream"
  },
  "facial_hair": {
    "patternName": "bushy_beard",
    "paletteName": "theme__032__desert_dream"
  },
  "eyewear": {
    "patternName": "ar_vr_visor",
    "paletteName": "transluscent_red"
  },
  "hair": {
    "patternName": "fohawk",
    "paletteName": "theme__032__desert_dream"
  }
}
